{
	"Album": [
		{
			"Type": "Mostro",
			"ID": 1,
			"Nome": "Murloc Tinyfin",
			"Effetto": "",
			"Mana": 0,
			"Rarita": "Comune",
			"Classe": "Neutrale",
			"Razza": "Murloc", 
			"Attacco": 1,
			"Difesa": 1
		},
		{
			"Type": "Mostro",
			"ID": 2,
			"Nome": "Snowflipper Penguin",
			"Effetto": "",
			"Mana": 0,
			"Rarita": "Comune",
			"Classe": "Neutrale",
			"Razza": "Bestia",
			"Attacco": 1,
			"Difesa": 1
		},
		{
			"Type": "Mostro",
			"ID": 3,
			"Nome": "Wisp",
			"Effetto": "",
			"Mana":0,
			"Rarita": "Comune",
			"Classe": "Neutrale",
			"Razza": "Comune",
			"Attacco": 1,
			"Difesa": 1
		},
		{
			"Type": "Mostro",
			"ID": 4,
			"Nome": "Elven Archer",
			"Effetto": "",
			"Mana": 1,
			"Rarita": "Comune",
			"Classe": "Neutrale",
			"Razza": "Comune",
			"Attacco": 1,
			"Difesa": 1
		},
		{
			"Type": "Mostro",
			"ID": 5,
			"Nome": "Helmet Hermit",
			"Effetto": "",
			"Mana": 1,
			"Rarita": "Rara",
			"Classe": "Neutrale",
			"Razza": "Bestia",
			"Attacco": 4,
			"Difesa": 3
		},
		{
			"Type": "Mostro",
			"ID": 6,
			"Nome": "Sir Finley Mrrgglton",
			"Effetto": "",
			"Mana": 1,
			"Rarita": "Leggendaria",
			"Classe": "Neutrale",
			"Razza": "Murloc",
			"Attacco": 1,
			"Difesa": 3
		},
		{
			"Type": "Mostro",
			"ID": 7,
			"Nome": "Acidic Swamp Ooze",
			"Effetto": "",
			"Mana": 2,
			"Rarita": "Rara",
			"Classe": "Neutrale",
			"Razza": "Comune",
			"Attacco": 3,
			"Difesa": 2
		},
		{
			"Type": "Mostro",
			"ID": 8,
			"Nome": "Bloodmage Thalnos",
			"Effetto": "",
			"Mana": 2,
			"Rarita": "Leggendaria",
			"Classe": "Neutrale",
			"Razza": "Comune",
			"Attacco": 1,
			"Difesa": 1
		},
		{
			"Type": "Mostro",
			"ID": 9,
			"Nome": "Doomsayer",
			"Effetto": "",
			"Mana": 2,
			"Rarita": "Epica",
			"Classe": "Neutrale",
			"Razza": "Comune",
			"Attacco": 0,
			"Difesa": 7
		},
		{
			"Type": "Mostro",
			"ID": 10,
			"Nome": "Acolyte of Pain",
			"Effetto": "",
			"Mana": 3,
			"Rarita": "Comune",
			"Classe": "Neutrale",
			"Razza": "Comune",
			"Attacco": 1,
			"Difesa": 3
		},
		{
			"Type": "Mostro",
			"ID": 11,
			"Nome": "Brann BronzeBeard",
			"Effetto": "",
			"Mana": 3,
			"Rarita": "Leggendaria",
			"Classe": "Neutrale",
			"Razza": "Comune",
			"Attacco": 2,
			"Difesa": 4
		},
		{
			"Type": "Mostro",
			"ID": 12,
			"Nome": "Ironbeak Owl",
			"Effetto": "",
			"Mana": 3,
			"Rarita": "Comune",
			"Classe": "Neutrale",
			"Razza": "Bestia",
			"Attacco": 2,
			"Difesa": 1
		},
		{
			"Type": "Mostro",
			"ID": 13,
			"Nome": "Southsea Captain",
			"Effetto": "",
			"Mana": 3,
			"Rarita": "Epica",
			"Classe": "Neutrale",
			"Razza": "Pirata",
			"Attacco": 3,
			"Difesa": 3
		},
		{
			"Type": "Mostro",
			"ID": 14,
			"Nome": "Sneaky Devil",
			"Effetto": "",
			"Mana": 4,
			"Rarita": "Comune",
			"Classe": "Neutrale",
			"Razza": "Demone",
			"Attacco": 2,
			"Difesa": 2
		},
		{
			"Type": "Mostro",
			"ID": 15,
			"Nome": "Big Game Hunter",
			"Effetto": "",
			"Mana": 4,
			"Rarita": "Epica",
			"Classe": "Neutrale",
			"Razza": "Comune",
			"Attacco": 4,
			"Difesa": 2
		},
		{
			"Type": "Mostro",
			"ID": 16,
			"Nome": "Defender of Argus",
			"Effetto": "",
			"Mana": 4,
			"Rarita": "Rara",
			"Classe": "Neutrale",
			"Razza": "Comune",
			"Attacco": 3,
			"Difesa": 3
		},
		{
			"Type": "Mostro",
			"ID": 17,
			"Nome": "Old Murk-Eye",
			"Effetto": "",
			"Mana": 4,
			"Rarita": "Leggendaria",
			"Classe": "Neutrale",
			"Razza": "Murloc",
			"Attacco": 2,
			"Difesa": 4
		},
		{
			"Type": "Mostro",
			"ID": 18,
			"Nome": "Azure Drake",
			"Effetto": "",
			"Mana": 5,
			"Rarita": "Rara",
			"Classe": "Neutrale",
			"Razza": "Drago",
			"Attacco": 4,
			"Difesa": 5
		},
		{
			"Type": "Mostro",
			"ID": 19,
			"Nome": "Burning Blade Acolyte",
			"Effetto": "",
			"Mana": 5,
			"Rarita": "Rara",
			"Classe": "Neutrale",
			"Razza": "Comune",
			"Attacco": 1,
			"Difesa": 1
		},
		{
			"Type": "Mostro",
			"ID": 20,
			"Nome": "Prince Malchezaar",
			"Effetto": "",
			"Mana": 5,
			"Rarita": "Leggendaria",
			"Classe": "Neutrale",
			"Razza": "Demone",
			"Attacco": 4,
			"Difesa": 5
		},
		{
			"Type": "Mostro",
			"ID": 21,
			"Nome": "Faceless Manipulator",
			"Effetto": "",
			"Mana": 5,
			"Rarita": "Epica",
			"Classe": "Neutrale",
			"Razza": "Comune",
			"Attacco": 3,
			"Difesa": 3
		},
		{
			"Type": "Mostro",
			"ID": 22,
			"Nome": "Leeeeroyyy Jenkinssss",
			"Effetto": "",
			"Mana": 5,
			"Rarita": "Leggendaria",
			"Classe": "Neutrale",
			"Razza": "Comune",
			"Attacco": 6,
			"Difesa": 2
		},
		{
			"Type": "Mostro",
			"ID": 23,
			"Nome": "Maexxna",
			"Effetto": "",
			"Mana": 6,
			"Rarita": "Leggendaria",
			"Classe": "Neutrale",
			"Razza": "Bestia",
			"Attacco": 2,
			"Difesa": 8
		},
		{
			"Type": "Mostro",
			"ID": 24,
			"Nome": "Reno Jackson",
			"Effetto": "",
			"Mana": 6,
			"Rarita": "Leggendaria",
			"Classe": "Neutrale",
			"Razza": "Comune",
			"Attacco": 4,
			"Difesa": 6
		},
		{
			"Type": "Mostro",
			"ID": 25,
			"Nome": "Sabeartooth Stalker",
			"Effetto": "",
			"Mana": 6,
			"Rarita": "Comune",
			"Classe": "Neutrale",
			"Razza": "Bestia",
			"Attacco": 8,
			"Difesa": 2
		},
		{
			"Type": "Mostro",
			"ID": 26,
			"Nome": "Baron Geddon",
			"Effetto": "",
			"Mana": 7,
			"Rarita": "Leggendaria",
			"Classe": "Neutrale",
			"Razza": "Elementale",
			"Attacco": 7,
			"Difesa": 7
		},
		{
			"Type": "Mostro",
			"ID": 27,
			"Nome": "Primordial Drake",
			"Effetto": "",
			"Mana": 8,
			"Rarita": "Epica",
			"Classe": "Neutrale",
			"Razza": "Drago",
			"Attacco": 4,
			"Difesa": 8
		},
		{
			"Type": "Mostro",
			"ID": 28,
			"Nome": "Majordomo ExeQTus",
			"Effetto": "",
			"Mana": 9,
			"Rarita": "Leggendaria",
			"Classe": "Neutrale",
			"Razza": "Comune",
			"Attacco": 9,
			"Difesa": 7
		},
		{
			"Type": "Mostro",
			"ID": 29,
			"Nome": "Deathwing",
			"Effetto": "",
			"Mana": 10,
			"Rarita": "Leggendaria",
			"Classe": "Neutrale",
			"Razza": "Drago",
			"Attacco": 12,
			"Difesa": 12
		},
		{
			"Type": "Mostro",
			"ID": 30,
			"Nome": "Lokholar the Ice Lord",
			"Effetto": "",
			"Mana": 10,
			"Rarita": "Leggendaria",
			"Classe": "Neutrale",
			"Razza": "Elementale",
			"Attacco": 8,
			"Difesa": 8
		},
		{
			"Type": "Mostro",
			"ID": 31,
			"Nome": "Alleycat",
		 	"Effetto": "",
		 	"Mana": 1,
		 	"Rarita": "Comune",
		 	"Classe": "Cacciatore",
		 	"Razza": "Bestia",
		 	"Attacco": 1,
		 	"Difesa": 1
		},
		{
			"Type": "Mostro",
			"ID": 32,
		 	"Nome": "Armorsmith",
		 	"Effetto": "",
		 	"Mana": 2,
		 	"Rarita": "Rara",
		 	"Classe": "Guerriero",
		 	"Razza": "Comune",
		 	"Attacco": 1,
		 	"Difesa": 4
		},
		{
			"Type": "Mostro",
			"ID": 33,
		 	"Nome": "Defias Cannoneer",
		 	"Effetto": "",
		 	"Mana": 3,
		 	"Rarita": "Comune",
		 	"Classe": "Guerriero",
		 	"Razza": "Pirata",
		 	"Attacco": 3,
		 	"Difesa": 3
		},
		{
			"Type": "Mostro",
			"ID": 34,
		 	"Nome": "Tidal Revenant",
		 	"Effetto": "",
		 	"Mana": 8,
		 	"Rarita": "Comune",
		 	"Classe": "Guerriero",
		 	"Razza": "Elementale",
		 	"Attacco": 5,
		 	"Difesa": 8
		},
		{
			"Type": "Mostro",
			"ID": 35,
		 	"Nome": "Edwin VanCleef",
		 	"Effetto": "",
		 	"Mana": 3,
		 	"Rarita": "Leggendaria",
		 	"Classe": "Ladro",
		 	"Razza": "Comune",
		 	"Attacco": 2,
		 	"Difesa": 2
		},
		{
			"Type": "Mostro",
			"ID": 36,
		 	"Nome": "SIU:7 Agent",
		 	"Effetto": "",
		 	"Mana": 3,
		 	"Rarita": "Rara",
		 	"Classe": "Ladro",
		 	"Razza": "Comune",
		 	"Attacco": 3,
		 	"Difesa": 3
		},
		{
			"Type": "Mostro",
			"ID": 37,
		 	"Nome": "Hullbreaker",
		 	"Effetto": "",
		 	"Mana": 4,
		 	"Rarita": "Rara",
		 	"Classe": "Ladro",
		 	"Razza": "Demone",
		 	"Attacco": 4,
		 	"Difesa": 3
		},
		{
			"Type": "Mostro",
			"ID": 48,
		 	"Nome": "Voidwalker",
		 	"Effetto": "",
		 	"Mana": 1,
		 	"Rarita": "Comune",
		 	"Classe": "Ladro",
		 	"Razza": "Demone",
		 	"Attacco": 1,
		 	"Difesa": 3
		},
		{
			"Type": "Segreto",
			"ID": 39,
		 	"Nome": "Snake Trap",
		 	"Effetto": "",
		 	"Mana": 2,
		 	"Rarita": "Epica",
		 	"Classe": "Cacciatore"
		},
		{
			"Type": "Segreto",
			"ID": 40,
		 	"Nome": "Bear Trap",
		 	"Effetto": "",
		 	"Mana": 2,
		 	"Rarita": "Comune",
		 	"Classe": "Cacciatore"
		},
		{
			"Type": "Segreto",
			"ID": 41,
		 	"Nome": "Ice Block",
		 	"Effetto": "",
		 	"Mana": 3,
		 	"Rarita": "Epica",
		 	"Classe": "Mago"
		},
		{
			"Type": "Magia",
			"ID": 42,
		 	"Nome": "Animal Companion",
		 	"Effetto": "",
		 	"Mana": 3,
		 	"Rarita": "Comune",
		 	"Classe": "Cacciatore"
		},
		{
			"Type": "Magia",
			"ID": 43,
		 	"Nome": "Brawl",
		 	"Effetto": "",
		 	"Mana": 5,
		 	"Rarita": "Epica",
		 	"Classe": "Guerriero"
		},
		{
			"Type": "Magia",
			"ID": 44,
		 	"Nome": "Backstab",
		 	"Effetto": "",
		 	"Mana": 0,
		 	"Rarita": "Comune",
		 	"Classe": "Ladro"
		},
		{
			"Type": "Magia",
			"ID": 45,
		 	"Nome": "Sprint",
		 	"Effetto": "",
		 	"Mana": 5,
		 	"Rarita": "Rara",
		 	"Classe": "Ladro"
		},
		{
			"Type": "Magia",
			"ID": 46,
		 	"Nome": "Arcane Intellect",
		 	"Effetto": "",
		 	"Mana": 3,
		 	"Rarita": "Comune",
		 	"Classe": "Mago"
		},
		{
			"Type": "Magia",
			"ID": 47,
		 	"Nome": "Shattering Blast",
		 	"Effetto": "",
		 	"Mana": 3,
		 	"Rarita": "Rara",
		 	"Classe": "Mago"
		},
		{
			"Type": "Magia",
			"ID": 48,
		 	"Nome": "Fireball",
		 	"Effetto": "",
		 	"Mana": 4,
		 	"Rarita": "Comune",
		 	"Classe": "Mago"
		},
		{
			"Type": "Magia",
			"ID": 49,
		 	"Nome": "Mortal Coil",
		 	"Effetto": "",
		 	"Mana": 1,
		 	"Rarita": "Comune",
		 	"Classe": "Ladro"
		},
		{
			"Type": "Magia",
			"ID": 50,
		 	"Nome": "Drain Soul",
		 	"Effetto": "",
		 	"Mana": 2,
		 	"Rarita": "Comune",
		 	"Classe": "Ladro"
		}
	]
}
